src/__init__.py
src/cloudwatch.py
src/configManager.py
src/ecs.py
src/main.py
src/ssm.py
src/task.py
run_fargate_task-1.0.0.dist-info/METADATA
run_fargate_task-1.0.0.dist-info/WHEEL
run_fargate_task-1.0.0.dist-info/entry_points.txt
run_fargate_task-1.0.0.dist-info/top_level.txt
run_fargate_task-1.0.0.dist-info/RECORD
