Metadata-Version: 2.1
Name: run-fargate-task
Version: 1.0.0
Summary: Script to trigger fargate tasks
Home-page: https://github.com/redaptiveinc/devops-scripts
Author: Mariano Gimenez
Author-email: mariano.gimenez@agileengine.com
License: unlicense
Platform: UNKNOWN
Requires-Dist: python-dotenv (==0.10.3)
Requires-Dist: boto3 (==1.10.7)
